validate_nigerian_phone/__init__.py
validate_nigerian_phone-1.0.0.dist-info/DESCRIPTION.rst
validate_nigerian_phone-1.0.0.dist-info/METADATA
validate_nigerian_phone-1.0.0.dist-info/RECORD
validate_nigerian_phone-1.0.0.dist-info/WHEEL
validate_nigerian_phone-1.0.0.dist-info/metadata.json
validate_nigerian_phone-1.0.0.dist-info/top_level.txt
