Metadata-Version: 2.0
Name: validate-nigerian-phone
Version: 1.0.0
Summary: Python Class to validate a Nigerian phone number as well as attempt to deduce the network
Home-page: https://github.com/djunehor/validate_nigerian_phone
Author: Zacchaeus Bolaji
Author-email: djunehor@gmail.com
License: UNKNOWN
Platform: UNKNOWN
